django_formit-0.1.3.dist-info/DESCRIPTION.rst
django_formit-0.1.3.dist-info/LICENSE.txt
django_formit-0.1.3.dist-info/METADATA
django_formit-0.1.3.dist-info/RECORD
django_formit-0.1.3.dist-info/WHEEL
django_formit-0.1.3.dist-info/metadata.json
django_formit-0.1.3.dist-info/top_level.txt
formit/__init__.py
formit/apps.py
formit/settings.py
formit/templates/formit/field.html
formit/templates/formit/fieldset.html
formit/templates/formit/form.html
formit/templatetags/__init__.py
formit/templatetags/formit_tags.py
