Metadata-Version: 2.0
Name: django-formit
Version: 0.1.3
Summary: Simple Django form formating
Home-page: https://github.com/dinoperovic/django-formit
Author: Dino Perovic
Author-email: dino.perovic@gmail.com
License: BSD License
Platform: OS Independent
Classifier: Environment :: Web Environment
Classifier: Framework :: Django
Classifier: Intended Audience :: Developers
Classifier: License :: OSI Approved :: BSD License
Classifier: Operating System :: OS Independent
Classifier: Programming Language :: Python :: 2.7
Classifier: Programming Language :: Python :: 3.4
Classifier: Programming Language :: Python :: 3.5
Requires-Dist: django-classy-tags (>=0.8.0)
